{"_id":{"$oid":"5f3be79c32dc85296bda189f"},"customer_name":"PT. NARA OKA PRAKARSA","customer_address":"JL. KH. AHMAD DAHLAN NO. 100, SEMARANG TENGAH 12420","customer_email":"info@naraoka.co.id","customer_phone":"024-1234567","customer_address_detail":null,"customer_zip_code":"12420","zone_code":"CGKFT","organization_id":{"$numberInt":"6"},"location_id":"5cecb20b6c49615b174c3e74","modified_at":null,"is_delete":false,"created_at":{"$date":{"$numberLong":"1597761436315"}},"__v":{"$numberInt":"0"}}
